tablets/__init__.py
tablets/admin.py
tablets/apps.py
tablets/backend.py
tablets/models.py
tablets/__pycache__/__init__.cpython-35.pyc
tablets/__pycache__/__init__.cpython-36.pyc
tablets/__pycache__/admin.cpython-35.pyc
tablets/__pycache__/admin.cpython-36.pyc
tablets/__pycache__/backend.cpython-35.pyc
tablets/__pycache__/models.cpython-35.pyc
tablets/__pycache__/models.cpython-36.pyc
tablets/j2/__init__.py
tablets/j2/exceptions.py
tablets/j2/loaders.py
tablets/j2/__pycache__/__init__.cpython-35.pyc
tablets/j2/__pycache__/__init__.cpython-36.pyc
tablets/j2/__pycache__/exceptions.cpython-35.pyc
tablets/j2/__pycache__/exceptions.cpython-36.pyc
tablets/j2/__pycache__/loaders.cpython-35.pyc
tablets/j2/__pycache__/loaders.cpython-36.pyc
tablets/loaders/__init__.py
tablets/loaders/database.py
tablets/loaders/__pycache__/__init__.cpython-36.pyc
tablets/loaders/__pycache__/database.cpython-35.pyc
tablets/loaders/__pycache__/database.cpython-36.pyc
tablets/migrations/0001_initial.py
tablets/migrations/0002_add_mptt.py
tablets/migrations/0003_auto_20180207_1349.py
tablets/migrations/__init__.py
tablets/migrations/__pycache__/0001_initial.cpython-35.pyc
tablets/migrations/__pycache__/0001_initial.cpython-36.pyc
tablets/migrations/__pycache__/0002_add_mptt.cpython-35.pyc
tablets/migrations/__pycache__/0002_add_mptt.cpython-36.pyc
tablets/migrations/__pycache__/0003_auto_20180207_1349.cpython-36.pyc
tablets/migrations/__pycache__/0003_jsonfield_switch.cpython-35.pyc
tablets/migrations/__pycache__/__init__.cpython-35.pyc
tablets/migrations/__pycache__/__init__.cpython-36.pyc
tablets/south_migrations/0001_initial.py
tablets/south_migrations/0002_adds_mptt.py
tablets/south_migrations/__init__.py
tablets-0.7.0.dist-info/DESCRIPTION.rst
tablets-0.7.0.dist-info/METADATA
tablets-0.7.0.dist-info/RECORD
tablets-0.7.0.dist-info/WHEEL
tablets-0.7.0.dist-info/metadata.json
tablets-0.7.0.dist-info/pbr.json
tablets-0.7.0.dist-info/top_level.txt
